<resources>
    <!-- Default screen margins, per the Android Design guidelines. -->
    <dimen name="nav_header_vertical_spacing">16dp</dimen>
    <dimen name="nav_header_height">160dp</dimen>
    <dimen name="padding_sides">36dp</dimen>
    <dimen name="margin_top_toolbar">0dp</dimen>
    <!-- Default screen margins, per the Android Design guidelines. -->
    <dimen name="activity_horizontal_margin">16dp</dimen>
    <dimen name="activity_vertical_margin">16dp</dimen>
    <dimen name="cardview_margin">15dp</dimen>
    <dimen name="previewseekbar_indicator_width">10dp</dimen>
    <dimen name="video_preview_width">160dp</dimen>
    <dimen name="video_preview_height">90dp</dimen>
    <dimen name="video_frame_width">2dp</dimen>
    <dimen name="textSize14">14sp</dimen>
    <dimen name="textSize16">16sp</dimen>
    <dimen name="textSize18">18sp</dimen>
    <dimen name="textSize20">20sp</dimen>
    <dimen name="textSize22">22sp</dimen>
    <dimen name="textSize24">24sp</dimen>
    <dimen name="textSize26">26sp</dimen>
    <dimen name="textSize28">28sp</dimen>
    <dimen name="textSize30">30sp</dimen>

    <dimen name="fullscreen_status_bar_height">0dp</dimen>
    <dimen name="action_bar_height">55dp</dimen>

    <!--CONCIERGE PAGE-->
    <dimen name="concierge_leftmenu_item_height">60dp</dimen>
    <dimen name="concierge_right_checkout_txtsize">16dp</dimen>
    <dimen name="concierge_right_checkout_txtsizetotal">18dp</dimen>

    <!--DIALOG-->
    <dimen name="overlay_div_width">250dp</dimen>
    <dimen name="overlay_div_height">200dp</dimen>
    <dimen name="parental_size">70dp</dimen>
</resources>
